norgatedata/CHANGES.txt
norgatedata/LICENSE.txt
norgatedata/__init__.py
norgatedata/api.py
norgatedata/norgatedata_release_version.json
norgatedata/norgatehelper.py
norgatedata/version.py
norgatedata-1.0.74.dist-info/LICENSE.TXT
norgatedata-1.0.74.dist-info/METADATA
norgatedata-1.0.74.dist-info/WHEEL
norgatedata-1.0.74.dist-info/top_level.txt
norgatedata-1.0.74.dist-info/RECORD
