Metadata-Version: 2.1
Name: norgatedata
Version: 1.0.74
Summary: Python interface to financial data provided by Norgate Data
Home-page: https://norgatedata.com
Author: NorgateData Pty Ltd
Author-email: support@norgatedata.com
License: EULA
Classifier: Intended Audience :: Financial and Insurance Industry
Classifier: Development Status :: 5 - Production/Stable
Classifier: Environment :: Win32 (MS Windows)
Classifier: Programming Language :: Python
Classifier: Programming Language :: Python :: 3
Classifier: Programming Language :: Python :: 3.5
Classifier: Programming Language :: Python :: 3.6
Classifier: Programming Language :: Python :: 3.7
Classifier: Programming Language :: Python :: 3.8
Classifier: Programming Language :: Python :: 3.9
Classifier: Programming Language :: Python :: 3.10
Classifier: License :: Other/Proprietary License
Classifier: Operating System :: Microsoft :: Windows
Classifier: Topic :: Office/Business :: Financial :: Investment
Requires-Python: >3.5.0
License-File: LICENSE.TXT
Requires-Dist: pandas
Requires-Dist: numpy
Requires-Dist: requests
Requires-Dist: logbook
